[{"__type__":"cc.SpriteFrame","content":{"name":"img_guessword_reel3","texture":"0f9+WiWQ9BjIpRXcN735fQ","rect":[0,0,612,61],"offset":[0,0],"originalSize":[612,61],"capInsets":[0,0,0,0]}},{"__type__":"cc.SpriteFrame","content":{"name":"t_guessword_2","texture":"c7bDkookJP4aIuFKiL26PA","rect":[0,0,20,27],"offset":[0,0],"originalSize":[20,27],"capInsets":[0,0,0,0]}},{"__type__":"cc.SpriteFrame","content":{"name":"t_guessword_4","texture":"98hAHW6DxPwYE4q6Zs05rt","rect":[0,0,20,27],"offset":[0,0],"originalSize":[20,27],"capInsets":[0,0,0,0]}},{"__type__":"cc.SpriteFrame","content":{"name":"btn_guessword_close","texture":"2d7jEhb/lNNaKBOIZafuKr","rect":[0,0,53,51],"offset":[0,0],"originalSize":[53,51],"capInsets":[0,0,0,0]}},{"__type__":"cc.SpriteFrame","content":{"name":"default_btn_disabled","texture":"71VhFCTINJM6/Ky3oX9nBT","rect":[0,0,40,40],"offset":[0,0],"originalSize":[40,40],"capInsets":[12,12,12,12]}},{"__type__":"cc.SpriteFrame","content":{"name":"t_guessword_1","texture":"0dYlYAIv1NpIvcuctEOUSf","rect":[0,0,20,27],"offset":[0,0],"originalSize":[20,27],"capInsets":[0,0,0,0]}},[{"__type__":"cc.Prefab","_name":"cell","data":{"__id__":1}},{"__type__":"cc.Node","_name":"cell","_children":[{"__id__":2},{"__id__":3}],"_level":1,"_components":[{"__type__":"cc.Sprite","node":{"__id__":1},"_spriteFrame":{"__uuid__":"dczwl+loZKVatrdFu9awh9"}},{"__type__":"cc.Button","node":{"__id__":1},"transition":3,"zoomScale":1.02,"clickEvents":[{"__type__":"cc.ClickEvent","target":{"__id__":1},"component":"Cell","handler":"jumpStage"}],"_N$target":{"__id__":1}},{"__type__":"6837fhFHWxPcoeE3S/lsfWv","node":{"__id__":1},"Label":{"__id__":2},"Lock":{"__id__":4}}],"_prefab":{"__type__":"cc.PrefabInfo","root":{"__id__":1},"asset":{"__uuid__":"47FyVbwh5AVK9Gjg4A1mzf"},"fileId":"fd7/+TNHdH7qStj/uvhOvl"},"_contentSize":{"__type__":"cc.Size","width":111,"height":111},"_position":{"__type__":"cc.Vec3","x":-189.5,"y":194.5},"_scale":{"__type__":"cc.Vec3","x":1,"y":1,"z":1}},{"__type__":"cc.Node","_name":"Label","_parent":{"__id__":1},"_level":4,"_components":[{"__type__":"ce76boNog9DKZ7MrQ8OYxnX","node":{"__id__":2},"numCell":{"__uuid__":"53sdSfEb1NCoZhkWn6akEA"}},{"__type__":"cc.Layout","node":{"__id__":2},"_resize":1,"_N$layoutType":1}],"_prefab":{"__type__":"cc.PrefabInfo","root":{"__id__":1},"asset":{"__uuid__":"47FyVbwh5AVK9Gjg4A1mzf"},"fileId":"31V4BqLYpE77BGJL9lqpTZ"},"_color":{"__type__":"cc.Color","r":245,"g":220,"b":144},"_contentSize":{"__type__":"cc.Size","width":23.46,"height":40},"_scale":{"__type__":"cc.Vec3","x":1,"y":1,"z":1}},{"__type__":"cc.Node","_name":"Lock","_parent":{"__id__":1},"_level":4,"_components":[{"__id__":4},{"__type__":"cc.Button","node":{"__id__":3},"_N$target":{"__id__":3}}],"_prefab":{"__type__":"cc.PrefabInfo","root":{"__id__":1},"asset":{"__uuid__":"47FyVbwh5AVK9Gjg4A1mzf"},"fileId":"d4EJGBCBFA3Z5resn1cK/V"},"_contentSize":{"__type__":"cc.Size","width":111,"height":111},"_scale":{"__type__":"cc.Vec3","x":1,"y":1,"z":1}},{"__type__":"cc.Sprite","node":{"__id__":3},"_spriteFrame":{"__uuid__":"e5T+aC7oxLSrcAwDGDKt2G"}}],[{"__type__":"cc.Prefab","_name":"NumCell","data":{"__id__":1}},{"__type__":"cc.Node","_name":"NumCell","_children":[{"__id__":2},{"__id__":3},{"__id__":4},{"__id__":5},{"__id__":6},{"__id__":7},{"__id__":8},{"__id__":9},{"__id__":10},{"__id__":11}],"_level":1,"_components":[{"__type__":"9d378K7+J5IpoztkjVPaZG1","node":{"__id__":1}}],"_prefab":{"__type__":"cc.PrefabInfo","root":{"__id__":1},"asset":{"__uuid__":"53sdSfEb1NCoZhkWn6akEA"},"fileId":"9d0xclDplO0qwe8XNYOrFs"},"_contentSize":{"__type__":"cc.Size","width":19,"height":27},"_scale":{"__type__":"cc.Vec3","x":1,"y":1,"z":1}},{"__type__":"cc.Node","_name":"0","_parent":{"__id__":1},"_active":false,"_level":2,"_components":[{"__type__":"cc.Sprite","node":{"__id__":2},"_spriteFrame":{"__uuid__":"97oM/S5S9ISKBvPlSoMq+J"}}],"_prefab":{"__type__":"cc.PrefabInfo","root":{"__id__":1},"asset":{"__uuid__":"53sdSfEb1NCoZhkWn6akEA"},"fileId":"e1pqA085VHXbGR/tPrtsNY"},"_contentSize":{"__type__":"cc.Size","width":19,"height":27},"_scale":{"__type__":"cc.Vec3","x":1,"y":1,"z":1}},{"__type__":"cc.Node","_name":"1","_parent":{"__id__":1},"_active":false,"_level":2,"_components":[{"__type__":"cc.Sprite","node":{"__id__":3},"_spriteFrame":{"__uuid__":"45ibh/BAxM+4cj89bCtmtq"}}],"_prefab":{"__type__":"cc.PrefabInfo","root":{"__id__":1},"asset":{"__uuid__":"53sdSfEb1NCoZhkWn6akEA"},"fileId":"ebQMXBAApMIqVhxL1VOT9J"},"_contentSize":{"__type__":"cc.Size","width":16,"height":25},"_scale":{"__type__":"cc.Vec3","x":1,"y":1,"z":1}},{"__type__":"cc.Node","_name":"2","_parent":{"__id__":1},"_active":false,"_level":2,"_components":[{"__type__":"cc.Sprite","node":{"__id__":4},"_spriteFrame":{"__uuid__":"07czDJk+dCDZReCmDdS7/s"}}],"_prefab":{"__type__":"cc.PrefabInfo","root":{"__id__":1},"asset":{"__uuid__":"53sdSfEb1NCoZhkWn6akEA"},"fileId":"4fvlmT5mJB+ZrtVA9Urkzo"},"_contentSize":{"__type__":"cc.Size","width":17,"height":26},"_scale":{"__type__":"cc.Vec3","x":1,"y":1,"z":1}},{"__type__":"cc.Node","_name":"3","_parent":{"__id__":1},"_active":false,"_level":2,"_components":[{"__type__":"cc.Sprite","node":{"__id__":5},"_spriteFrame":{"__uuid__":"f2ehaFC+BHU6CESMc9xScw"}}],"_prefab":{"__type__":"cc.PrefabInfo","root":{"__id__":1},"asset":{"__uuid__":"53sdSfEb1NCoZhkWn6akEA"},"fileId":"c5sLoaPodHKoDm/WOReQx/"},"_contentSize":{"__type__":"cc.Size","width":19,"height":27},"_scale":{"__type__":"cc.Vec3","x":1,"y":1,"z":1}},{"__type__":"cc.Node","_name":"4","_parent":{"__id__":1},"_active":false,"_level":2,"_components":[{"__type__":"cc.Sprite","node":{"__id__":6},"_spriteFrame":{"__uuid__":"07/hWRV1dAPoUYeIPW6au2"}}],"_prefab":{"__type__":"cc.PrefabInfo","root":{"__id__":1},"asset":{"__uuid__":"53sdSfEb1NCoZhkWn6akEA"},"fileId":"9bRU8FVRZFwIu7rZpzgGhw"},"_contentSize":{"__type__":"cc.Size","width":20,"height":26},"_scale":{"__type__":"cc.Vec3","x":1,"y":1,"z":1}},{"__type__":"cc.Node","_name":"5","_parent":{"__id__":1},"_active":false,"_level":2,"_components":[{"__type__":"cc.Sprite","node":{"__id__":7},"_spriteFrame":{"__uuid__":"55zVAOTSlF/5GYqWzhxdU/"}}],"_prefab":{"__type__":"cc.PrefabInfo","root":{"__id__":1},"asset":{"__uuid__":"53sdSfEb1NCoZhkWn6akEA"},"fileId":"d6LbwMj6JBdagh0HNc7wCC"},"_contentSize":{"__type__":"cc.Size","width":17,"height":26},"_scale":{"__type__":"cc.Vec3","x":1,"y":1,"z":1}},{"__type__":"cc.Node","_name":"6","_parent":{"__id__":1},"_active":false,"_level":2,"_components":[{"__type__":"cc.Sprite","node":{"__id__":8},"_spriteFrame":{"__uuid__":"f4LWFxB0dPwIczmVldNYf1"}}],"_prefab":{"__type__":"cc.PrefabInfo","root":{"__id__":1},"asset":{"__uuid__":"53sdSfEb1NCoZhkWn6akEA"},"fileId":"04BmwZ8iBLz5w5WLYsgdhQ"},"_contentSize":{"__type__":"cc.Size","width":18,"height":27},"_scale":{"__type__":"cc.Vec3","x":1,"y":1,"z":1}},{"__type__":"cc.Node","_name":"7","_parent":{"__id__":1},"_active":false,"_level":2,"_components":[{"__type__":"cc.Sprite","node":{"__id__":9},"_spriteFrame":{"__uuid__":"c7qp80HPxOwJwdnREQEfq5"}}],"_prefab":{"__type__":"cc.PrefabInfo","root":{"__id__":1},"asset":{"__uuid__":"53sdSfEb1NCoZhkWn6akEA"},"fileId":"bcgMzhgOxF3IWvJNQZFW21"},"_contentSize":{"__type__":"cc.Size","width":18,"height":26},"_scale":{"__type__":"cc.Vec3","x":1,"y":1,"z":1}},{"__type__":"cc.Node","_name":"8","_parent":{"__id__":1},"_active":false,"_level":2,"_components":[{"__type__":"cc.Sprite","node":{"__id__":10},"_spriteFrame":{"__uuid__":"efzKRVyLZGkJ6G7tesIFp5"}}],"_prefab":{"__type__":"cc.PrefabInfo","root":{"__id__":1},"asset":{"__uuid__":"53sdSfEb1NCoZhkWn6akEA"},"fileId":"77DtwSMltIva6cqpxpKVpW"},"_contentSize":{"__type__":"cc.Size","width":18,"height":27},"_scale":{"__type__":"cc.Vec3","x":1,"y":1,"z":1}},{"__type__":"cc.Node","_name":"9","_parent":{"__id__":1},"_active":false,"_level":2,"_components":[{"__type__":"cc.Sprite","node":{"__id__":11},"_spriteFrame":{"__uuid__":"c7nHTtXUpOfLPw89Ne6c7P"}}],"_prefab":{"__type__":"cc.PrefabInfo","root":{"__id__":1},"asset":{"__uuid__":"53sdSfEb1NCoZhkWn6akEA"},"fileId":"9fJU6pf2FJZb5Q4o37Jn3K"},"_contentSize":{"__type__":"cc.Size","width":18,"height":27},"_scale":{"__type__":"cc.Vec3","x":1,"y":1,"z":1}}],{"__type__":"cc.SpriteFrame","content":{"name":"t_guessword_5","texture":"03SZ2k7F9M0bGf2HD8TMzL","rect":[0,0,20,27],"offset":[0,0],"originalSize":[20,27],"capInsets":[0,0,0,0]}},{"__type__":"cc.SpriteFrame","content":{"name":"img_gword_amount_gray","texture":"ceTe+jmzJOz7bghtn5nd3z","rect":[0,0,27,26],"offset":[0,0.5],"originalSize":[27,27],"capInsets":[0,0,0,0]}},{"__type__":"cc.SpriteFrame","content":{"name":"panel_guessword_title","texture":"283tpI9V5G06CZuPRdiYzm","rect":[1,0,468,48],"offset":[0,0],"originalSize":[470,48],"capInsets":[0,0,0,0]}},{"__type__":"cc.SpriteFrame","content":{"name":"btn_gword_arrow","texture":"50sf5mltBEb7MUFXDM4JQx","rect":[0,0,46,95],"offset":[0,0],"originalSize":[46,95],"capInsets":[0,0,0,0]}},{"__type__":"cc.SpriteFrame","content":{"name":"t_guessword_0","texture":"e1tOv6olNHz41/r797QLZs","rect":[0,0,20,27],"offset":[0,0],"originalSize":[20,27],"capInsets":[0,0,0,0]}},{"__type__":"cc.SpriteFrame","content":{"name":"default_panel","texture":"d8HsitJHxOYqo801xBk8ev","rect":[0,0,20,20],"offset":[0,0],"originalSize":[20,20],"capInsets":[6,6,6,6]}},{"__type__":"cc.SpriteFrame","content":{"name":"default_sprite_splash","texture":"02delMVqdBD70a/HSD99FK","rect":[0,0,2,2],"offset":[0,0],"originalSize":[2,2],"capInsets":[0,0,0,0]}},{"__type__":"cc.SpriteFrame","content":{"name":"img_gword_amount_light","texture":"66p4c49CdAo6IoPhS7Tp3Y","rect":[0,0,21,24],"offset":[0,0],"originalSize":[21,24],"capInsets":[0,0,0,0]}},[{"__type__":"cc.Prefab","_name":"point","data":{"__id__":1}},{"__type__":"cc.Node","_name":"point","_children":[{"__id__":2},{"__id__":3}],"_level":3,"_prefab":{"__type__":"cc.PrefabInfo","root":{"__id__":1},"asset":{"__id__":0},"fileId":"d5PtIMSyND84mqme/eEhPO"},"_contentSize":{"__type__":"cc.Size","width":27,"height":27},"_scale":{"__type__":"cc.Vec3","x":1,"y":1,"z":1}},{"__type__":"cc.Node","_name":"unselect","_parent":{"__id__":1},"_level":4,"_components":[{"__type__":"cc.Sprite","node":{"__id__":2},"_spriteFrame":{"__uuid__":"57Evfs4VdCSZfl/wCGrIg9"}}],"_prefab":{"__type__":"cc.PrefabInfo","root":{"__id__":1},"asset":{"__id__":0},"fileId":"29wn/4HQxLFKn7we5TPuxg"},"_contentSize":{"__type__":"cc.Size","width":27,"height":26},"_scale":{"__type__":"cc.Vec3","x":1,"y":1,"z":1}},{"__type__":"cc.Node","_name":"select","_parent":{"__id__":1},"_level":4,"_components":[{"__type__":"cc.Sprite","node":{"__id__":3},"_spriteFrame":{"__uuid__":"aemsmNxuBIoLWg0Du+f9A3"}}],"_prefab":{"__type__":"cc.PrefabInfo","root":{"__id__":1},"asset":{"__id__":0},"fileId":"465ah4MXhEpp65yrfv2KwA"},"_contentSize":{"__type__":"cc.Size","width":21,"height":24},"_scale":{"__type__":"cc.Vec3","x":1,"y":1,"z":1}}],[{"__type__":"cc.Prefab","_name":"StagePop","data":{"__id__":1}},{"__type__":"cc.Node","_name":"PopStage","_children":[{"__id__":2},{"__id__":3},{"__id__":7},{"__id__":11},{"__id__":12},{"__id__":13},{"__id__":14},{"__id__":15}],"_level":1,"_components":[{"__type__":"5ca377LGhtI3rI0nlPfn5NR","node":{"__id__":1},"point":{"__uuid__":"b454O8u11D3IYsLQUBNmh5"},"cell":{"__uuid__":"47FyVbwh5AVK9Gjg4A1mzf"},"content":{"__id__":13},"title":{"__id__":9},"RighrArrow":{"__id__":11},"LeftArrow":{"__id__":12},"PagePoint":{"__id__":14},"lockMask":{"__id__":15}}],"_prefab":{"__type__":"cc.PrefabInfo","root":{"__id__":1},"asset":{"__uuid__":"c2HWkdp8tBfpVJiqAPQty0"},"fileId":"c43iT3tFBBWIje1hoXxeGu"},"_scale":{"__type__":"cc.Vec3","x":1,"y":1,"z":1}},{"__type__":"cc.Node","_name":"mask","_parent":{"__id__":1},"_level":2,"_components":[{"__type__":"cc.Sprite","node":{"__id__":2},"_spriteFrame":{"__uuid__":"a2MjXRFdtLlYQ5ouAFv/+R"},"_sizeMode":0},{"__type__":"cc.Button","node":{"__id__":2},"_N$target":{"__id__":2}}],"_prefab":{"__type__":"cc.PrefabInfo","root":{"__id__":1},"asset":{"__uuid__":"c2HWkdp8tBfpVJiqAPQty0"},"fileId":"97V4ok41pAB4jyBIuNSNgt"},"_opacity":204,"_color":{"__type__":"cc.Color"},"_contentSize":{"__type__":"cc.Size","width":640,"height":1136},"_scale":{"__type__":"cc.Vec3","x":1,"y":1,"z":1}},{"__type__":"cc.Node","_name":"bg","_parent":{"__id__":1},"_children":[{"__id__":4},{"__id__":5},{"__id__":6}],"_level":2,"_prefab":{"__type__":"cc.PrefabInfo","root":{"__id__":1},"asset":{"__uuid__":"c2HWkdp8tBfpVJiqAPQty0"},"fileId":"12zlDPVEdKSayVqJEaoxp9"},"_contentSize":{"__type__":"cc.Size","width":300,"height":200},"_scale":{"__type__":"cc.Vec3","x":1,"y":1,"z":1}},{"__type__":"cc.Node","_name":"head","_parent":{"__id__":3},"_level":3,"_components":[{"__type__":"cc.Sprite","node":{"__id__":4},"_spriteFrame":{"__uuid__":"feXgY9dJdHPasvSMN2PCtM"}}],"_prefab":{"__type__":"cc.PrefabInfo","root":{"__id__":1},"asset":{"__uuid__":"c2HWkdp8tBfpVJiqAPQty0"},"fileId":"3ag90GN2tHur/eXYfV3GHd"},"_contentSize":{"__type__":"cc.Size","width":612,"height":61},"_position":{"__type__":"cc.Vec3","y":436},"_scale":{"__type__":"cc.Vec3","x":1,"y":1,"z":1}},{"__type__":"cc.Node","_name":"mid","_parent":{"__id__":3},"_level":3,"_components":[{"__type__":"cc.Sprite","node":{"__id__":5},"_spriteFrame":{"__uuid__":"c9YiY6AexO0aBfxILM/0CG"},"_type":2,"_sizeMode":0}],"_prefab":{"__type__":"cc.PrefabInfo","root":{"__id__":1},"asset":{"__uuid__":"c2HWkdp8tBfpVJiqAPQty0"},"fileId":"d46qc9/NtDRLkiO/lVt3K2"},"_contentSize":{"__type__":"cc.Size","width":582,"height":600},"_position":{"__type__":"cc.Vec3","y":109},"_scale":{"__type__":"cc.Vec3","x":1,"y":1,"z":1}},{"__type__":"cc.Node","_name":"foot","_parent":{"__id__":3},"_level":3,"_components":[{"__type__":"cc.Sprite","node":{"__id__":6},"_spriteFrame":{"__uuid__":"01t/9tmT1Ea7onDFvqRORs"}}],"_prefab":{"__type__":"cc.PrefabInfo","root":{"__id__":1},"asset":{"__uuid__":"c2HWkdp8tBfpVJiqAPQty0"},"fileId":"d3jiBmfS1OwYIlttA2/pek"},"_contentSize":{"__type__":"cc.Size","width":612,"height":61},"_position":{"__type__":"cc.Vec3","y":-221},"_scale":{"__type__":"cc.Vec3","x":1,"y":1,"z":1}},{"__type__":"cc.Node","_name":"TitleBG","_parent":{"__id__":1},"_children":[{"__id__":8},{"__id__":10}],"_level":2,"_components":[{"__type__":"cc.Sprite","node":{"__id__":7},"_spriteFrame":{"__uuid__":"5a4DKzmwlB9buHoAj1xV77"}}],"_prefab":{"__type__":"cc.PrefabInfo","root":{"__id__":1},"asset":{"__uuid__":"c2HWkdp8tBfpVJiqAPQty0"},"fileId":"c64F0DPxRKNbwWd1RZFxLt"},"_contentSize":{"__type__":"cc.Size","width":468,"height":48},"_position":{"__type__":"cc.Vec3","y":385},"_scale":{"__type__":"cc.Vec3","x":1,"y":1,"z":1}},{"__type__":"cc.Node","_name":"Label","_parent":{"__id__":7},"_level":4,"_components":[{"__id__":9}],"_prefab":{"__type__":"cc.PrefabInfo","root":{"__id__":1},"asset":{"__uuid__":"c2HWkdp8tBfpVJiqAPQty0"},"fileId":"07oTJUmbhEe7EvBZBsUGol"},"_color":{"__type__":"cc.Color","r":243,"g":234,"b":221},"_contentSize":{"__type__":"cc.Size","width":66,"height":22},"_scale":{"__type__":"cc.Vec3","x":1,"y":1,"z":1}},{"__type__":"cc.Label","node":{"__id__":8},"_srcBlendFactor":1,"_useOriginalSize":false,"_string":"小宝宝","_N$string":"小宝宝","_fontSize":22,"_lineHeight":22,"_N$horizontalAlign":1,"_N$verticalAlign":1,"_N$fontFamily":"微软雅黑"},{"__type__":"cc.Node","_name":"close","_parent":{"__id__":7},"_level":3,"_components":[{"__type__":"cc.Sprite","node":{"__id__":10},"_spriteFrame":{"__uuid__":"0bN06QZddOpZC9/mIehWHv"},"_type":1,"_sizeMode":0},{"__type__":"cc.Button","node":{"__id__":10},"transition":3,"pressedColor":{"__type__":"cc.Color","r":255,"g":255,"b":255},"zoomScale":1.08,"clickEvents":[{"__type__":"cc.ClickEvent","target":{"__id__":1},"component":"StagePop","handler":"close"}],"_N$normalColor":{"__type__":"cc.Color","r":255,"g":255,"b":255},"_N$disabledColor":{"__type__":"cc.Color","r":255,"g":255,"b":255},"_N$normalSprite":{"__uuid__":"f0BIwQ8D5Ml7nTNQbh1YlS"},"_N$pressedSprite":{"__uuid__":"e97GVMl6JHh5Ml5qEDdSGa"},"pressedSprite":{"__uuid__":"e97GVMl6JHh5Ml5qEDdSGa"},"_N$hoverSprite":{"__uuid__":"f0BIwQ8D5Ml7nTNQbh1YlS"},"hoverSprite":{"__uuid__":"f0BIwQ8D5Ml7nTNQbh1YlS"},"_N$disabledSprite":{"__uuid__":"29FYIk+N1GYaeWH/q1NxQO"},"_N$target":{"__id__":10}}],"_prefab":{"__type__":"cc.PrefabInfo","root":{"__id__":1},"asset":{"__uuid__":"c2HWkdp8tBfpVJiqAPQty0"},"fileId":"247UYIz3NLapRfXR22ILfv"},"_contentSize":{"__type__":"cc.Size","width":53,"height":51},"_position":{"__type__":"cc.Vec3","x":240,"y":1},"_scale":{"__type__":"cc.Vec3","x":1,"y":1,"z":1}},{"__type__":"cc.Node","_name":"RighrArrow","_parent":{"__id__":1},"_level":2,"_components":[{"__type__":"cc.Sprite","node":{"__id__":11},"_spriteFrame":{"__uuid__":"87WOJQOVdNDaUMnJN2K99K"}},{"__type__":"cc.Button","node":{"__id__":11},"transition":3,"zoomScale":1.08,"clickEvents":[{"__type__":"cc.ClickEvent","target":{"__id__":1},"component":"StagePop","handler":"pageRight"}],"_N$target":{"__id__":11}}],"_prefab":{"__type__":"cc.PrefabInfo","root":{"__id__":1},"asset":{"__uuid__":"c2HWkdp8tBfpVJiqAPQty0"},"fileId":"faCh194BlAvK2tWfYmttq8"},"_contentSize":{"__type__":"cc.Size","width":46,"height":95},"_position":{"__type__":"cc.Vec3","x":288.3,"y":101},"_scale":{"__type__":"cc.Vec3","x":1,"y":1,"z":1}},{"__type__":"cc.Node","_name":"LeftArrow","_parent":{"__id__":1},"_level":2,"_components":[{"__type__":"cc.Sprite","node":{"__id__":12},"_spriteFrame":{"__uuid__":"87WOJQOVdNDaUMnJN2K99K"}},{"__type__":"cc.Button","node":{"__id__":12},"transition":3,"zoomScale":1.08,"clickEvents":[{"__type__":"cc.ClickEvent","target":{"__id__":1},"component":"StagePop","handler":"pageLeft"}],"_N$target":{"__id__":12}}],"_prefab":{"__type__":"cc.PrefabInfo","root":{"__id__":1},"asset":{"__uuid__":"c2HWkdp8tBfpVJiqAPQty0"},"fileId":"32uld1yeJBzJwaikTjz9Oq"},"_contentSize":{"__type__":"cc.Size","width":46,"height":95},"_position":{"__type__":"cc.Vec3","x":-286,"y":101},"_scale":{"__type__":"cc.Vec3","x":-1,"y":-1,"z":1}},{"__type__":"cc.Node","_name":"Page","_parent":{"__id__":1},"_level":2,"_components":[{"__type__":"cc.Sprite","node":{"__id__":13},"_enabled":false,"_spriteFrame":{"__uuid__":"9bvaMerUlDyary99mJa6xp"},"_type":1,"_sizeMode":0},{"__type__":"cc.Layout","node":{"__id__":13},"_layoutSize":{"__type__":"cc.Size","width":500,"height":500},"_N$layoutType":3,"_N$paddingLeft":5,"_N$paddingRight":5,"_N$spacingX":15,"_N$spacingY":15}],"_prefab":{"__type__":"cc.PrefabInfo","root":{"__id__":1},"asset":{"__uuid__":"c2HWkdp8tBfpVJiqAPQty0"},"fileId":"b8rJCE2hND2LVCEndvgc6w"},"_color":{"__type__":"cc.Color","r":167,"g":167,"b":167},"_contentSize":{"__type__":"cc.Size","width":500,"height":500},"_position":{"__type__":"cc.Vec3","y":101},"_scale":{"__type__":"cc.Vec3","x":1,"y":1,"z":1}},{"__type__":"cc.Node","_name":"PagePoint","_parent":{"__id__":1},"_active":false,"_level":2,"_components":[{"__type__":"cc.Layout","node":{"__id__":14},"_layoutSize":{"__type__":"cc.Size","width":27,"height":27},"_resize":1,"_N$layoutType":1,"_N$spacingX":10}],"_prefab":{"__type__":"cc.PrefabInfo","root":{"__id__":1},"asset":{"__uuid__":"c2HWkdp8tBfpVJiqAPQty0"},"fileId":"04abzknJJJkaz/9z2HsZ/c"},"_contentSize":{"__type__":"cc.Size","width":27,"height":27},"_position":{"__type__":"cc.Vec3","y":-190},"_scale":{"__type__":"cc.Vec3","x":1,"y":1,"z":1}},{"__type__":"cc.Node","_name":"lockMask","_parent":{"__id__":1},"_active":false,"_level":2,"_components":[{"__type__":"cc.Sprite","node":{"__id__":15},"_spriteFrame":{"__uuid__":"a2MjXRFdtLlYQ5ouAFv/+R"},"_sizeMode":0},{"__type__":"cc.Button","node":{"__id__":15},"_N$target":{"__id__":15}}],"_prefab":{"__type__":"cc.PrefabInfo","root":{"__id__":1},"asset":{"__uuid__":"c2HWkdp8tBfpVJiqAPQty0"},"fileId":"cbiojWaiFCAr7zfgjanGVC"},"_opacity":0,"_color":{"__type__":"cc.Color"},"_contentSize":{"__type__":"cc.Size","width":640,"height":1136},"_scale":{"__type__":"cc.Vec3","x":1,"y":1,"z":1}}],{"__type__":"cc.SpriteFrame","content":{"name":"t_guessword_9","texture":"61XmiCdCdAUKEMnVfwzCxq","rect":[0,0,20,27],"offset":[0,0],"originalSize":[20,27],"capInsets":[0,0,0,0]}},{"__type__":"cc.SpriteFrame","content":{"name":"t_guessword_7","texture":"9d2Hay1YlLo6ldKfaDibP0","rect":[0,0,20,27],"offset":[0,0],"originalSize":[20,27],"capInsets":[0,0,0,0]}},{"__type__":"cc.SpriteFrame","content":{"name":"img_guessword_reel2","texture":"54wEKqllFD8ooe2DW/cp9j","rect":[0,0,582,29],"offset":[0,0],"originalSize":[582,29],"capInsets":[0,0,0,0]}},{"__type__":"cc.SpriteFrame","content":{"name":"img_guessword_level1","texture":"9fTXxR1n5HwZ9FqxscO/vT","rect":[0,0,111,111],"offset":[0,0],"originalSize":[111,111],"capInsets":[0,0,0,0]}},{"__type__":"cc.SpriteFrame","content":{"name":"img_guessword_level2","texture":"06Yd9KkZdLyKktEmMu9QSc","rect":[0,0,111,111],"offset":[0,0],"originalSize":[111,111],"capInsets":[0,0,0,0]}},{"__type__":"cc.SpriteFrame","content":{"name":"default_btn_pressed","texture":"b4P/PCArtIdIH38t6mlw8Y","rect":[0,0,40,40],"offset":[0,0],"originalSize":[40,40],"capInsets":[12,12,12,12]}},{"__type__":"cc.SpriteFrame","content":{"name":"t_guessword_8","texture":"8a25+fQANMh5LcIhC6eaP2","rect":[0,0,20,27],"offset":[0,0],"originalSize":[20,27],"capInsets":[0,0,0,0]}},{"__type__":"cc.SpriteFrame","content":{"name":"default_btn_normal","texture":"e8Ueib+qJEhL6mXAHdnwbi","rect":[0,0,40,40],"offset":[0,0],"originalSize":[40,40],"capInsets":[12,12,12,12]}},{"__type__":"cc.SpriteFrame","content":{"name":"t_guessword_3","texture":"2angOxPyJEAJtSnX2ar/EM","rect":[0,0,20,27],"offset":[0,0],"originalSize":[20,27],"capInsets":[0,0,0,0]}},{"__type__":"cc.SpriteFrame","content":{"name":"t_guessword_6","texture":"71Vmf6qhFDg7B4QFMXgTqu","rect":[0,0,20,27],"offset":[0,0],"originalSize":[20,27],"capInsets":[0,0,0,0]}},{"__type__":"cc.SpriteFrame","content":{"name":"img_guessword_reel1","texture":"04qmllyO5HnpP8meHOgHC7","rect":[0,0,612,61],"offset":[0,0],"originalSize":[612,61],"capInsets":[0,0,0,0]}}]